flask_cf_framework/__init__.py
flask_cf_framework/cors.py
flask_cf_framework/endpoint.py
flask_cf_framework/log.py
flask_cf_framework/request_handler.py
flask_cf_framework/tests/__init__.py
flask_cf_framework/tests/test_user.py
flask_cf_framework-0.0.14.dist-info/LICENSE
flask_cf_framework-0.0.14.dist-info/METADATA
flask_cf_framework-0.0.14.dist-info/WHEEL
flask_cf_framework-0.0.14.dist-info/top_level.txt
flask_cf_framework-0.0.14.dist-info/RECORD
